musictune/__init__.py
musictune/UI/__init__.py
musictune/UI/cli.py
musictune/UI/simplegui.py
musictune/adjustments/__init__.py
musictune/adjustments/parallel.py
musictune/adjustments/single.py
musictune/data/Weights.json
musictune/data/line_profile.csv
musictune/data/line_profile.h5
musictune/data/save_path.json
musictune/data/PSF/CV_us_561_fine.tif
musictune/data/PSF/CV_us_640_fine.tif
musictune/data/PSF/PSF_16bit_full.tif
musictune/deconvolution/__init__.py
musictune/deconvolution/deconv_mappings.py
musictune/deconvolution/deconvolve.py
musictune/deconvolution/fftwWisdom.py
musictune/deconvolution/psf.py
musictune/deconvolution/richardsonLucy.py
musictune/io/PZFFormat.py
musictune/io/PZF_Zstd.py
musictune/io/PZF_conversion.py
musictune/io/Zarr_stitching.py
musictune/io/__init__.py
musictune/io/delayed_from_zarr.py
musictune/io/modules.py
musictune/io/old_stitch.py
musictune/io/params.py
musictune/io/utilities.py
musictune/pzf2zarr/PZF_Zstd.py
musictune/pzf2zarr/__init__.py
musictune/pzf2zarr/channel.py
musictune/pzf2zarr/config.py
musictune/pzf2zarr/params.py
musictune/pzf2zarr/session.py
musictune/pzf2zarr/stack.py
musictune/pzf2zarr/strip.py
musictune/pzf2zarr/utilities.py
musictune/pzf2zarr/scripts/__init__.py
musictune/pzf2zarr/scripts/scout.py
musictune/scripts/__init__.py
musictune/scripts/block.py
musictune/scripts/block_fast.py
musictune/scripts/pzf2zarr.py
musictune/scripts/scout.py
musictune/scripts/scout_fast.py
musictune/scripts/scout_greg.py
musictune/scripts/start_cluster.py
musictune/scripts/stitching.py
musictune/scripts/zarr2tif.py
musictune-0.0.13.dist-info/LICENSE
musictune-0.0.13.dist-info/METADATA
musictune-0.0.13.dist-info/WHEEL
musictune-0.0.13.dist-info/entry_points.txt
musictune-0.0.13.dist-info/top_level.txt
musictune-0.0.13.dist-info/RECORD
